odoo/addons/mail_outbound_static/README.rst
odoo/addons/mail_outbound_static/__init__.py
odoo/addons/mail_outbound_static/__manifest__.py
odoo/addons/mail_outbound_static/i18n/es.po
odoo/addons/mail_outbound_static/i18n/mail_outbound_static.pot
odoo/addons/mail_outbound_static/i18n/pt.po
odoo/addons/mail_outbound_static/models/__init__.py
odoo/addons/mail_outbound_static/models/ir_mail_server.py
odoo/addons/mail_outbound_static/readme/CONTRIBUTORS.rst
odoo/addons/mail_outbound_static/readme/DESCRIPTION.rst
odoo/addons/mail_outbound_static/readme/ROADMAP.rst
odoo/addons/mail_outbound_static/readme/USAGE.rst
odoo/addons/mail_outbound_static/static/description/icon.png
odoo/addons/mail_outbound_static/static/description/index.html
odoo/addons/mail_outbound_static/tests/__init__.py
odoo/addons/mail_outbound_static/tests/test.msg
odoo/addons/mail_outbound_static/tests/test_ir_mail_server.py
odoo/addons/mail_outbound_static/views/ir_mail_server_view.xml
odoo14_addon_mail_outbound_static-14.0.2.0.1.dist-info/METADATA
odoo14_addon_mail_outbound_static-14.0.2.0.1.dist-info/WHEEL
odoo14_addon_mail_outbound_static-14.0.2.0.1.dist-info/top_level.txt
odoo14_addon_mail_outbound_static-14.0.2.0.1.dist-info/RECORD
