Metadata-Version: 2.1
Name: odoo14-addon-mail-outbound-static
Version: 14.0.2.0.1
Summary: Allows you to configure the from header for a mail server.
Home-page: https://github.com/OCA/social
Author: brain-tec AG, LasLabs, Adhoc SA, Odoo Community Association (OCA)
Author-email: support@odoo-community.org
License: LGPL-3
Platform: UNKNOWN
Classifier: Programming Language :: Python
Classifier: Framework :: Odoo
Classifier: Framework :: Odoo :: 14.0
Classifier: License :: OSI Approved :: GNU Lesser General Public License v3 (LGPLv3)
Requires-Python: >=3.6
Requires-Dist: odoo <14.1dev,>=14.0a
